cubicweb_forgotpwd/__init__.py
cubicweb_forgotpwd/__pkginfo__.py
cubicweb_forgotpwd/entities.py
cubicweb_forgotpwd/hooks.py
cubicweb_forgotpwd/schema.py
cubicweb_forgotpwd/site_cubicweb.py
cubicweb_forgotpwd/sobjects.py
cubicweb_forgotpwd/views.py
cubicweb_forgotpwd/i18n/en.po
cubicweb_forgotpwd/i18n/es.po
cubicweb_forgotpwd/i18n/fr.po
cubicweb_forgotpwd/migration/0.3.0_Any.py
cubicweb_forgotpwd/migration/postcreate.py
cubicweb_forgotpwd/migration/precreate.py
cubicweb_forgotpwd/wdoc/ChangeLog_en
cubicweb_forgotpwd/wdoc/ChangeLog_fr
cubicweb_forgotpwd-1.0.0.dist-info/METADATA
cubicweb_forgotpwd-1.0.0.dist-info/WHEEL
cubicweb_forgotpwd-1.0.0.dist-info/entry_points.txt
cubicweb_forgotpwd-1.0.0.dist-info/top_level.txt
cubicweb_forgotpwd-1.0.0.dist-info/RECORD
