Metadata-Version: 2.1
Name: cubicweb-forgotpwd
Version: 1.0.0
Summary: password recovery component for the CubicWeb framework
Home-page: https://forge.extranet.logilab.fr/cubicweb/cubes/cubicweb-forgotpwd
Author: LOGILAB S.A. (Paris, FRANCE)
Author-email: contact@logilab.fr
License: LGPL
Classifier: Environment :: Web Environment
Classifier: Framework :: CubicWeb
Classifier: Programming Language :: Python
Classifier: Programming Language :: JavaScript
Requires-Dist: cubicweb[crypto] (<5.0.0,>=4.0.0)
Requires-Dist: cubicweb-web (<2.0.0,>=1.0.0)
Requires-Dist: Pillow
Requires-Dist: six
